stringdale/__init__.py
stringdale/_modidx.py
stringdale/base.py
stringdale/chat.py
stringdale/core.py
stringdale/db.py
stringdale/declerative.py
stringdale/diagrams_old.py
stringdale/doc.py
stringdale/eval.py
stringdale/execution.py
stringdale/mappings.py
stringdale/serialize.py
stringdale/stream_warping.py
stringdale/tools.py
stringdale/utils.py
stringdale/viz.py
stringdale/examples/__init__.py
stringdale/examples/rag.py
stringdale/examples/react.py
stringdale-0.5.0.dist-info/METADATA
stringdale-0.5.0.dist-info/WHEEL
stringdale-0.5.0.dist-info/licenses/LICENSE
stringdale-0.5.0.dist-info/RECORD
