Metadata-Version: 2.4
Name: StringDALE
Version: 0.5.0
Summary: String Diagram Agent Language Express (StringDALE) is a language for building LLM agents using string diagrams.
License-File: LICENSE
Requires-Python: >=3.10
Requires-Dist: bidict>=0.23.1
Requires-Dist: chromadb>=1.0.15
Requires-Dist: deepdiff>=8.5.0
Requires-Dist: deepmerge>=2.0
Requires-Dist: fastcore>=1.8.5
Requires-Dist: frozendict>=2.4.6
Requires-Dist: google-search-results>=2.4.2
Requires-Dist: graphviz>=0.21
Requires-Dist: html2text>=2025.4.15
Requires-Dist: instructor>=1.10.0
Requires-Dist: ipython>=8
Requires-Dist: isodate>=0.7.2
Requires-Dist: jinja2>=3.1.6
Requires-Dist: joblib>=1.5.1
Requires-Dist: jsonlines>=4.0.0
Requires-Dist: lark>=1.2.2
Requires-Dist: nest-asyncio>=1.6.0
Requires-Dist: networkx>=3.3
Requires-Dist: openai>=1.97.1
Requires-Dist: pandas>=2.3.1
Requires-Dist: parse>=1.20.2
Requires-Dist: pillow>=11.3.0
Requires-Dist: prettyprint>=0.1.5
Requires-Dist: python-constraint2>=2.4.0
Requires-Dist: python-dotenv>=1.1.1
Requires-Dist: python-git>=2018.2.1
Requires-Dist: singleton-decorator>=1.0.0
Requires-Dist: smolagents>=1.20.0
Requires-Dist: sqlmodel>=0.0.24
Requires-Dist: wikipedia>=1.4.0
